setup.py
faeriebot/__init__.py
faeriebot.egg-info/PKG-INFO
faeriebot.egg-info/SOURCES.txt
faeriebot.egg-info/dependency_links.txt
faeriebot.egg-info/not-zip-safe
faeriebot.egg-info/top_level.txt