Metadata-Version: 1.0
Name: faeriebot
Version: 0.1
Summary: Flowing Accounts for Electronically Recording Income & Expenses Bot
Home-page: http://github.com/ivanwangsa/faeriebot
Author: Ivan Wangsa
Author-email: ivanwangsa@gmail.com
License: MIT
Platform: UNKNOWN
